tansa/__init__.py
tansa/app.py
tansa/finder.py
tansa/jreader.py
tansa/jwriter.py
tansa-0.0.1.dist-info/LICENSE.txt
tansa-0.0.1.dist-info/METADATA
tansa-0.0.1.dist-info/WHEEL
tansa-0.0.1.dist-info/entry_points.txt
tansa-0.0.1.dist-info/top_level.txt
tansa-0.0.1.dist-info/RECORD
