Metadata-Version: 2.1
Name: tansa
Version: 0.0.1
Summary: JSON extractor from file path
Home-page: https://github.com/k0a8t1o6/tansa
Author: Takashi Kato
Author-email: taka@m.atelierpal.space
License: UNKNOWN
Platform: UNKNOWN
Classifier: Programming Language :: Python :: 3.5
Classifier: Programming Language :: Python :: 3.6
Classifier: Programming Language :: Python :: 3.7
Classifier: Programming Language :: Python :: 3.8
Classifier: License :: OSI Approved :: MIT License
Classifier: Operating System :: OS Independent
